httpwatcher/__init__.py
httpwatcher/cmdline.py
httpwatcher/errors.py
httpwatcher/filesystem.py
httpwatcher/server.py
httpwatcher/scripts/httpwatcher.bundle.js
httpwatcher/scripts/httpwatcher.min.js
httpwatcher-0.5.2.dist-info/LICENSE
httpwatcher-0.5.2.dist-info/LICENSE.md
httpwatcher-0.5.2.dist-info/METADATA
httpwatcher-0.5.2.dist-info/WHEEL
httpwatcher-0.5.2.dist-info/entry_points.txt
httpwatcher-0.5.2.dist-info/top_level.txt
httpwatcher-0.5.2.dist-info/RECORD
