Metadata-Version: 1.1
Name: httpwatcher
Version: 0.5.2
Summary: Web server library and command-line utility for serving static files with live reload functionality
Home-page: https://github.com/thanethomson/httpwatcher
Author: Thane Thomson
Author-email: connect@thanethomson.com
License: MIT
Keywords: livereload hotreload web server live reload hot reload
Platform: UNKNOWN
Classifier: Development Status :: 4 - Beta
Classifier: Environment :: Console
Classifier: Intended Audience :: Developers
Classifier: License :: OSI Approved :: MIT License
Classifier: Natural Language :: English
Classifier: Operating System :: POSIX
Classifier: Operating System :: MacOS
Classifier: Programming Language :: Python :: 2
Classifier: Programming Language :: Python :: 2.7
Classifier: Programming Language :: Python :: 3
Classifier: Programming Language :: Python :: 3.5
Classifier: Programming Language :: Python :: 3.6
Classifier: Topic :: Internet :: WWW/HTTP
Classifier: Topic :: Utilities
